icalcli/__init__.py
icalcli/argparsers.py
icalcli/icalcli.py
icalcli/printer.py
icalcli/utils.py
icalcli/etesync_backend/__init__.py
icalcli/etesync_backend/etebase_crud.py
icalcli/etesync_backend/etebase_interface.py
icalcli/etesync_backend/etesync_crud.py
icalcli/etesync_backend/etesync_interface.py
icalcli/etesync_backend/example_.icalcli.py
icalcli/file_backend/__init__.py
icalcli/file_backend/ics_interface.py
icalcli-1.1.3.dist-info/LICENSE
icalcli-1.1.3.dist-info/METADATA
icalcli-1.1.3.dist-info/WHEEL
icalcli-1.1.3.dist-info/entry_points.txt
icalcli-1.1.3.dist-info/top_level.txt
icalcli-1.1.3.dist-info/RECORD
