Metadata-Version: 2.1
Name: icalcli
Version: 1.1.3
Summary: Icalendar Calendar Command Line Interface
Home-page: https://github.com/jrvarma/icalcli
Maintainer: Jayanth R. Varma
Maintainer-email: jrvarma@gmail.com
Classifier: Development Status :: 3 - Alpha
Classifier: Environment :: Console
Classifier: Intended Audience :: End Users/Desktop
Classifier: License :: OSI Approved :: MIT License
Classifier: Programming Language :: Python :: 3
Requires-Python: >=3.6
License-File: LICENSE
Requires-Dist: python-dateutil
Requires-Dist: parsedatetime
Requires-Dist: icalendar
Requires-Dist: recurring-ical-events
Provides-Extra: parsedatetime
Requires-Dist: parsedatetime; extra == "parsedatetime"
